imgcvrt.py
imgcvrt-1.0.0.dist-info/WHEEL
imgcvrt-1.0.0.dist-info/METADATA
imgcvrt-1.0.0.dist-info/RECORD
