Metadata-Version: 2.1
Name: imgcvrt
Version: 1.0.0
Summary: Convert("filename").toIco("filename")
Author: TimurALTron
Author-email: slaveallaha7777@gmail.com
Requires-Python: >=3.6,<4.0
Classifier: Programming Language :: Python :: 3
Classifier: Programming Language :: Python :: 3.6
Classifier: Programming Language :: Python :: 3.7
Classifier: Programming Language :: Python :: 3.8
